MusicApp.py
PhanMemMMN-0.0.5.dist-info/METADATA
PhanMemMMN-0.0.5.dist-info/WHEEL
PhanMemMMN-0.0.5.dist-info/top_level.txt
PhanMemMMN-0.0.5.dist-info/RECORD
