Metadata-Version: 2.1
Name: PhanMemMMN
Version: 0.0.5
Summary: A music player package for Linux
Author: ViDat
Author-email: tiendatopip@gmail.com
Requires-Dist: pygame
Requires-Dist: numpy
Requires-Dist: Pillow
Requires-Dist: customtkinter
